datestuff/__init__.py
datestuff/_comparable.py
datestuff/daterange.py
datestuff/relative.py
datestuff/utils.py
datestuff-0.3.0.dist-info/METADATA
datestuff-0.3.0.dist-info/RECORD
datestuff-0.3.0.dist-info/WHEEL
datestuff-0.3.0.dist-info/top_level.txt
