Metadata-Version: 2.1
Name: datestuff
Version: 0.3.0
Summary: Stuff for dates
Home-page: https://github.com/justanr/datestuff
Author: Alec Nikolas Reiter
Author-email: alecreiter@gmail.com
License: MIT
Keywords: dates,datetime
Platform: UNKNOWN
Classifier: Development Status :: 3 - Alpha
Classifier: Topic :: Utilities
Classifier: Intended Audience :: Developers
Classifier: License :: OSI Approved :: MIT License
Classifier: Programming Language :: Python :: 2.7
Classifier: Programming Language :: Python :: 3.4
Classifier: Programming Language :: Python :: 3.5
Classifier: Programming Language :: Python :: 3.6
Classifier: Programming Language :: Python :: 3.7
